[
  {
    "LicenseNum": "1000442.558 ",
    "MultiJNum": ".",
    "BusinessName": "21st Century Productions ",
    "PrimaryJurisdiction": "Clark County ",
    "NonPrimaryJurisdiction": " ",
    "LicenseStatus": "Licensed ",
    "BusinessAddress": "3621 Asiago Ct North Las Vegas, NV 89032"
  },
  {
    "LicenseNum": "2003585.507 ",
    "MultiJNum": ".",
    "BusinessName": "3D Janitorial ",
    "PrimaryJurisdiction": "Clark County ",
    "NonPrimaryJurisdiction": " ",
    "LicenseStatus": "Licensed ",
    "BusinessAddress": "611 Park Landing Ct North Las Vegas, NV 89032"
  },
  {
    "LicenseNum": "2001501.GAM-105 ",
    "MultiJNum": ".",
    "BusinessName": "7-Eleven Store #32943D ",
    "PrimaryJurisdiction": "Clark County ",
    "NonPrimaryJurisdiction": " ",
    "LicenseStatus": "Licensed ",
    "BusinessAddress": "2935 W Lake Mead Blvd North Las Vegas, NV 89032"
  },
  {
    "LicenseNum": "2000830.071-121 ",
    "MultiJNum": ".",
    "BusinessName": "702 HELICOPTER, INC. ",
    "PrimaryJurisdiction": "Clark County ",
    "NonPrimaryJurisdiction": " ",
    "LicenseStatus": "Licensed ",
    "BusinessAddress": "2634 Airport Dr  Ste 101North Las Vegas, NV 89032"
  },
  {
    "LicenseNum": "2000368.508 ",
    "MultiJNum": ".",
    "BusinessName": "A Vision Carpet & Upholstery Maintenance And More ",
    "PrimaryJurisdiction": "Clark County ",
    "NonPrimaryJurisdiction": " ",
    "LicenseStatus": "Licensed ",
    "BusinessAddress": "836 Quicksand Ln North Las Vegas, NV 89032"
  },
  {
    "LicenseNum": "2001499.510 ",
    "MultiJNum": ".",
    "BusinessName": "A Vision Carpet & Upholstery Maintenance And More ",
    "PrimaryJurisdiction": "Clark County ",
    "NonPrimaryJurisdiction": " ",
    "LicenseStatus": "Licensed ",
    "BusinessAddress": "836 Quicksand Ln North Las Vegas, NV 89032"
  },
  {
    "LicenseNum": "2000799.845 ",
    "MultiJNum": ".",
    "BusinessName": "A-Tom-IC Solar Screens, Inc. ",
    "PrimaryJurisdiction": "Clark County ",
    "NonPrimaryJurisdiction": " ",
    "LicenseStatus": "Licensed ",
    "BusinessAddress": "3425 W Lake Mead Blvd  Suite 100North Las Vegas, NV 89032"
  },
  {
    "LicenseNum": "2000119.062-190 ",
    "MultiJNum": ".",
    "BusinessName": "Accelerated Learning Clinic ",
    "PrimaryJurisdiction": "Clark County ",
    "NonPrimaryJurisdiction": " ",
    "LicenseStatus": "Licensed ",
    "BusinessAddress": "3465 W Craig RdNorth Las Vegas, NV 89032"
  },
  {
    "LicenseNum": "2001606.543 ",
    "MultiJNum": ".",
    "BusinessName": "Advantage Cable Services, Inc ",
    "PrimaryJurisdiction": "Clark County ",
    "NonPrimaryJurisdiction": " ",
    "LicenseStatus": "Licensed ",
    "BusinessAddress": "3365 W Craig Rd  Ste 1North Las Vegas, NV 89032"
  },
  {
    "LicenseNum": "2001694.510 ",
    "MultiJNum": ".",
    "BusinessName": "Alarcon & Company LLC ",
    "PrimaryJurisdiction": "Clark County ",
    "NonPrimaryJurisdiction": " ",
    "LicenseStatus": "Licensed ",
    "BusinessAddress": "3532 Quiet Pueblo St North Las Vegas, NV 89032"
  },
  {
    "LicenseNum": "2002319.062-101 ",
    "MultiJNum": ".",
    "BusinessName": "Alexandra Tait LMT ",
    "PrimaryJurisdiction": "Clark County ",
    "NonPrimaryJurisdiction": " ",
    "LicenseStatus": "Revoked - Delinquent ",
    "BusinessAddress": "1237 W Alexander Rd  Unit 135North Las Vegas, NV 89032"
  },
  {
    "LicenseNum": "2000010.841 ",
    "MultiJNum": ".",
    "BusinessName": "ALL My Sons Moving & Storage of Las Vegas, Inc. ",
    "PrimaryJurisdiction": "Clark County ",
    "NonPrimaryJurisdiction": " ",
    "LicenseStatus": "Licensed ",
    "BusinessAddress": "2975 Coleman St North Las Vegas, NV 89032"
  },
  {
    "LicenseNum": "2000060.960 ",
    "MultiJNum": ".",
    "BusinessName": "American Lung Association of Nevada ",
    "PrimaryJurisdiction": "Clark County ",
    "NonPrimaryJurisdiction": " ",
    "LicenseStatus": "Licensed ",
    "BusinessAddress": "3552 W Cheyenne Ave  Ste #130North Las Vegas, NV 89032"
  },
  {
    "LicenseNum": "2000128.048-101 ",
    "MultiJNum": ".",
    "BusinessName": "American Spirit Tours, LLC ",
    "PrimaryJurisdiction": "Clark County ",
    "NonPrimaryJurisdiction": " ",
    "LicenseStatus": "Licensed ",
    "BusinessAddress": "2642 Airport DrNorth Las Vegas, NV 89032"
  },
  {
    "LicenseNum": "2000418.081-122 ",
    "MultiJNum": ".",
    "BusinessName": "Andrew L. Beals ",
    "PrimaryJurisdiction": "Clark County ",
    "NonPrimaryJurisdiction": " ",
    "LicenseStatus": "Revoked - Delinquent ",
    "BusinessAddress": "2807 Glory View Ln North Las Vegas, NV 89032"
  },
  {
    "LicenseNum": "2002155.048-122 ",
    "MultiJNum": ".",
    "BusinessName": "Arnel Cabras Cabigas ",
    "PrimaryJurisdiction": "Clark County ",
    "NonPrimaryJurisdiction": " ",
    "LicenseStatus": "Licensed ",
    "BusinessAddress": "1014 Melic WyNorth Las Vegas, NV 89032"
  },
  {
    "LicenseNum": "2000283.050 ",
    "MultiJNum": ".",
    "BusinessName": "Atcher Service LLC ",
    "PrimaryJurisdiction": "Clark County ",
    "NonPrimaryJurisdiction": " ",
    "LicenseStatus": "Revoked - Delinquent ",
    "BusinessAddress": "4032 Hatch StNorth Las Vegas, NV 89032"
  },
  {
    "LicenseNum": "2002265.510 ",
    "MultiJNum": ".",
    "BusinessName": "Best Quality Resurfacing, LLC ",
    "PrimaryJurisdiction": "Clark County ",
    "NonPrimaryJurisdiction": " ",
    "LicenseStatus": "Licensed ",
    "BusinessAddress": "2101 Hassell Ave North Las Vegas, NV 89032"
  },
  {
    "LicenseNum": "1001430.845 ",
    "MultiJNum": ".",
    "BusinessName": "Black Magic ",
    "PrimaryJurisdiction": "Clark County ",
    "NonPrimaryJurisdiction": " ",
    "LicenseStatus": "Licensed ",
    "BusinessAddress": "1411 Watercreek Dr North Las Vegas, NV 89032"
  },
  {
    "LicenseNum": "2003563.LIQ-117 ",
    "MultiJNum": ".",
    "BusinessName": "Breakthru Beverage Nevada Beer, LLC ",
    "PrimaryJurisdiction": "Clark County ",
    "NonPrimaryJurisdiction": " ",
    "LicenseStatus": "Temporary License ",
    "BusinessAddress": "1849 W Cheyenne Ave North Las Vegas, NV 89032"
  },
  {
    "LicenseNum": "2003562.LIQ-117 ",
    "MultiJNum": ".",
    "BusinessName": "Breakthru Beverage Nevada, LLC ",
    "PrimaryJurisdiction": "Clark County ",
    "NonPrimaryJurisdiction": " ",
    "LicenseStatus": "Temporary License ",
    "BusinessAddress": "1849 W Cheyenne Ave North Las Vegas, NV 89032"
  },
  {
    "LicenseNum": "2000574.845 ",
    "MultiJNum": ".",
    "BusinessName": "Breath Of Life Basic Life Support Training ",
    "PrimaryJurisdiction": "Clark County ",
    "NonPrimaryJurisdiction": " ",
    "LicenseStatus": "Licensed ",
    "BusinessAddress": "309 Moonlight Glow Ave North Las Vegas, NV 89032"
  },
  {
    "LicenseNum": "2002435.062-101 ",
    "MultiJNum": ".",
    "BusinessName": "Brianne Gaither Massage Therapist ",
    "PrimaryJurisdiction": "Clark County ",
    "NonPrimaryJurisdiction": " ",
    "LicenseStatus": "Licensed ",
    "BusinessAddress": "3327 Flying Colt CtNorth Las Vegas, NV 89032"
  },
  {
    "LicenseNum": "2000910.056-120 ",
    "MultiJNum": ".",
    "BusinessName": "Brillante Solution Services ",
    "PrimaryJurisdiction": "Clark County ",
    "NonPrimaryJurisdiction": " ",
    "LicenseStatus": "Revoked - Delinquent ",
    "BusinessAddress": "3913 Branchwood DrNorth Las Vegas, NV 89032"
  },
  {
    "LicenseNum": "1002396.GAM-105 ",
    "MultiJNum": ".",
    "BusinessName": "Cardivan, LLC ",
    "PrimaryJurisdiction": "Clark County ",
    "NonPrimaryJurisdiction": " ",
    "LicenseStatus": "Licensed ",
    "BusinessAddress": "1408 W Craig RdNorth Las Vegas, NV 89032"
  },
  {
    "LicenseNum": "2000113.GAM-105 ",
    "MultiJNum": ".",
    "BusinessName": "Cardivan, LLC ",
    "PrimaryJurisdiction": "Clark County ",
    "NonPrimaryJurisdiction": " ",
    "LicenseStatus": "Licensed ",
    "BusinessAddress": "4800 W Craig RdNorth Las Vegas, NV 89032"
  },
  {
    "LicenseNum": "2000110.411 ",
    "MultiJNum": ".",
    "BusinessName": "Carefree Catering ",
    "PrimaryJurisdiction": "Clark County ",
    "NonPrimaryJurisdiction": " ",
    "LicenseStatus": "Licensed ",
    "BusinessAddress": "439 Rock Quarry Way North Las Vegas, NV 89032"
  },
  {
    "LicenseNum": "2000091.GAM-105 ",
    "MultiJNum": ".",
    "BusinessName": "Carey Mini Mart ",
    "PrimaryJurisdiction": "Clark County ",
    "NonPrimaryJurisdiction": " ",
    "LicenseStatus": "Licensed ",
    "BusinessAddress": "1504 W Carey Ave North Las Vegas, NV 89032"
  },
  {
    "LicenseNum": "2001381.048-122 ",
    "MultiJNum": ".",
    "BusinessName": "Carlos E. Handabaka ",
    "PrimaryJurisdiction": "Clark County ",
    "NonPrimaryJurisdiction": " ",
    "LicenseStatus": "Licensed ",
    "BusinessAddress": "3825 Craig Crossing Dr  Apt# 3040North Las Vegas, NV 89032"
  },
  {
    "LicenseNum": "2001115.048-122 ",
    "MultiJNum": ".",
    "BusinessName": "Carlos Villarta Gregorio Jr. ",
    "PrimaryJurisdiction": "Clark County ",
    "NonPrimaryJurisdiction": " ",
    "LicenseStatus": "Licensed ",
    "BusinessAddress": "213 Spur Ranch AveNorth Las Vegas, NV 89032"
  },
  {
    "LicenseNum": "2000301.GAM-105 ",
    "MultiJNum": ".",
    "BusinessName": "Century Gaming Technologies ",
    "PrimaryJurisdiction": "Clark County ",
    "NonPrimaryJurisdiction": " ",
    "LicenseStatus": "Licensed ",
    "BusinessAddress": "2914 W Cheyenne Ave North Las Vegas, NV 89032"
  },
  {
    "LicenseNum": "1001436.845 ",
    "MultiJNum": ".",
    "BusinessName": "Chem Aqua Inc ",
    "PrimaryJurisdiction": "Clark County ",
    "NonPrimaryJurisdiction": " ",
    "LicenseStatus": "Licensed ",
    "BusinessAddress": "570 W Cheyenne Ave Suite 110North Las Vegas, NV 89032"
  },
  {
    "LicenseNum": "1001016.845 ",
    "MultiJNum": ".",
    "BusinessName": "Cimarron Materials Of Las Vegas ",
    "PrimaryJurisdiction": "Clark County ",
    "NonPrimaryJurisdiction": " ",
    "LicenseStatus": "Licensed ",
    "BusinessAddress": "203 W Delhi Ave North Las Vegas, NV 89032"
  },
  {
    "LicenseNum": "2000092.960 ",
    "MultiJNum": ".",
    "BusinessName": "Clark County Parent Cooperative, Inc. dba Kids' Co-Op ",
    "PrimaryJurisdiction": "Clark County ",
    "NonPrimaryJurisdiction": " ",
    "LicenseStatus": "Licensed ",
    "BusinessAddress": "4316 N Decatur BlvdNorth Las Vegas, NV 89032"
  },
  {
    "LicenseNum": "2000613.960 ",
    "MultiJNum": ".",
    "BusinessName": "Community Cat Coalition of Clark County ",
    "PrimaryJurisdiction": "Clark County ",
    "NonPrimaryJurisdiction": " ",
    "LicenseStatus": "Licensed ",
    "BusinessAddress": "4516 W San Miguel Ave North Las Vegas, NV 89032"
  },
  {
    "LicenseNum": "1001164.845 ",
    "MultiJNum": ".",
    "BusinessName": "Company Portable Restrooms Inc, A ",
    "PrimaryJurisdiction": "Clark County ",
    "NonPrimaryJurisdiction": " ",
    "LicenseStatus": "Licensed ",
    "BusinessAddress": "2701 Simmons St North Las Vegas, NV 89032"
  },
  {
    "LicenseNum": "2000447.048-122 ",
    "MultiJNum": ".",
    "BusinessName": "Conrad Co Jr ",
    "PrimaryJurisdiction": "Clark County ",
    "NonPrimaryJurisdiction": " ",
    "LicenseStatus": "Licensed ",
    "BusinessAddress": "3460 Canter DrNorth Las Vegas, NV 89032"
  },
  {
    "LicenseNum": "2000072.411 ",
    "MultiJNum": ".",
    "BusinessName": "Cukis ",
    "PrimaryJurisdiction": "Clark County ",
    "NonPrimaryJurisdiction": " ",
    "LicenseStatus": "Licensed ",
    "BusinessAddress": "439 Rock Quarry WyNorth Las Vegas, NV 89032"
  },
  {
    "LicenseNum": "2000475.048-122 ",
    "MultiJNum": ".",
    "BusinessName": "Delbert R Friesen ",
    "PrimaryJurisdiction": "Clark County ",
    "NonPrimaryJurisdiction": " ",
    "LicenseStatus": "Licensed ",
    "BusinessAddress": "4009 Aaron Scott StNorth Las Vegas, NV 89032"
  },
  {
    "LicenseNum": "2001536.056-120 ",
    "MultiJNum": ".",
    "BusinessName": "Diamond Lawn and Trees Services,LLC ",
    "PrimaryJurisdiction": "Clark County ",
    "NonPrimaryJurisdiction": " ",
    "LicenseStatus": "Licensed ",
    "BusinessAddress": "3204 Wembley CtNorth Las Vegas, NV 89032"
  },
  {
    "LicenseNum": "2000269.330 ",
    "MultiJNum": ".",
    "BusinessName": "Diamond Transport ",
    "PrimaryJurisdiction": "Clark County ",
    "NonPrimaryJurisdiction": " ",
    "LicenseStatus": "Licensed ",
    "BusinessAddress": "3532 Silver Lantern Dr North Las Vegas, NV 89032"
  },
  {
    "LicenseNum": "2000344.960 ",
    "MultiJNum": ".",
    "BusinessName": "Diversified Community Services Community Development Corporation ",
    "PrimaryJurisdiction": "Clark County ",
    "NonPrimaryJurisdiction": " ",
    "LicenseStatus": "Licensed ",
    "BusinessAddress": "3925 N Martin L King Blvd Suite 208North Las Vegas, NV 89032"
  },
  {
    "LicenseNum": "2001669.048-122 ",
    "MultiJNum": ".",
    "BusinessName": "DONALD DE ANTON JOHNSON ",
    "PrimaryJurisdiction": "Clark County ",
    "NonPrimaryJurisdiction": " ",
    "LicenseStatus": "Licensed ",
    "BusinessAddress": "932 High Altitude AveNorth Las Vegas, NV 89032"
  },
  {
    "LicenseNum": "2000352.048-122 ",
    "MultiJNum": ".",
    "BusinessName": "Donald S. Rogers ",
    "PrimaryJurisdiction": "Clark County ",
    "NonPrimaryJurisdiction": " ",
    "LicenseStatus": "Licensed ",
    "BusinessAddress": "4530 San Juan Ave North Las Vegas, NV 89032"
  },
  {
    "LicenseNum": "2001505.GAM-105 ",
    "MultiJNum": ".",
    "BusinessName": "Dotty's #53 ",
    "PrimaryJurisdiction": "Clark County ",
    "NonPrimaryJurisdiction": " ",
    "LicenseStatus": "Licensed ",
    "BusinessAddress": "1366 W Cheyenne Ave Ste 112 & 113North Las Vegas, NV 89032"
  },
  {
    "LicenseNum": "2001533.GAM-105 ",
    "MultiJNum": ".",
    "BusinessName": "Dotty's #67 ",
    "PrimaryJurisdiction": "Clark County ",
    "NonPrimaryJurisdiction": " ",
    "LicenseStatus": "Licensed ",
    "BusinessAddress": "2795 W Lake Mead Blvd  Lot 1-1-2North Las Vegas, NV 89032"
  },
  {
    "LicenseNum": "2002748.062-101 ",
    "MultiJNum": ".",
    "BusinessName": "Drake Little ",
    "PrimaryJurisdiction": "Clark County ",
    "NonPrimaryJurisdiction": " ",
    "LicenseStatus": "Licensed ",
    "BusinessAddress": "827 Mandolin WayNorth Las Vegas, NV 89032"
  },
  {
    "LicenseNum": "2000384.571 ",
    "MultiJNum": ".",
    "BusinessName": "Dungarvin Nevada, LLC ",
    "PrimaryJurisdiction": "Clark County ",
    "NonPrimaryJurisdiction": " ",
    "LicenseStatus": "Licensed ",
    "BusinessAddress": "3325 W Craig Rd  Ste ANorth Las Vegas, NV 89032"
  },
  {
    "LicenseNum": "1000984.845 ",
    "MultiJNum": ".",
    "BusinessName": "E & H Distributing Co ",
    "PrimaryJurisdiction": "Clark County ",
    "NonPrimaryJurisdiction": " ",
    "LicenseStatus": "Licensed ",
    "BusinessAddress": "1685 W Cheyenne Ave North Las Vegas, NV 89032"
  },
  {
    "LicenseNum": "2001748.072-201 ",
    "MultiJNum": ".",
    "BusinessName": "El Buen Taco ",
    "PrimaryJurisdiction": "Clark County ",
    "NonPrimaryJurisdiction": " ",
    "LicenseStatus": "Pending ",
    "BusinessAddress": "439 Rock Quarry WyNorth Las Vegas, NV 89032"
  },
  {
    "LicenseNum": "2002030.048-122 ",
    "MultiJNum": ".",
    "BusinessName": "Eliana Rosas ",
    "PrimaryJurisdiction": "Clark County ",
    "NonPrimaryJurisdiction": " ",
    "LicenseStatus": "Licensed ",
    "BusinessAddress": "3940 Scott Robinson Blvd  Unit 1018North Las Vegas, NV 89032"
  },
  {
    "LicenseNum": "2000391.048-122 ",
    "MultiJNum": ".",
    "BusinessName": "Eugene P Lewis ",
    "PrimaryJurisdiction": "Clark County ",
    "NonPrimaryJurisdiction": " ",
    "LicenseStatus": "Licensed ",
    "BusinessAddress": "4023 Benevolent DrNorth Las Vegas, NV 89032"
  },
  {
    "LicenseNum": "2002094.056-120 ",
    "MultiJNum": ".",
    "BusinessName": "Evergreen Lawn Services ",
    "PrimaryJurisdiction": "Clark County ",
    "NonPrimaryJurisdiction": " ",
    "LicenseStatus": "Licensed ",
    "BusinessAddress": "2509 Jubilance Point Ct North Las Vegas, NV 89032"
  },
  {
    "LicenseNum": "2000839.GAM-105 ",
    "MultiJNum": ".",
    "BusinessName": "Fabulous Freddy's Car Wash ",
    "PrimaryJurisdiction": "Clark County ",
    "NonPrimaryJurisdiction": " ",
    "LicenseStatus": "Licensed ",
    "BusinessAddress": "4309 W Craig Rd North Las Vegas, NV 89032"
  },
  {
    "LicenseNum": "2001501.072-201 ",
    "MultiJNum": ".",
    "BusinessName": "Family Ice Cream ",
    "PrimaryJurisdiction": "Clark County ",
    "NonPrimaryJurisdiction": " ",
    "LicenseStatus": "Licensed ",
    "BusinessAddress": "439 Rock Quarry WyNorth Las Vegas, NV 89032"
  },
  {
    "LicenseNum": "1003843.GAM-105 ",
    "MultiJNum": ".",
    "BusinessName": "Fiesta Hotel & Casino ",
    "PrimaryJurisdiction": "Clark County ",
    "NonPrimaryJurisdiction": " ",
    "LicenseStatus": "Licensed ",
    "BusinessAddress": "2400 N Rancho DrNorth Las Vegas, NV 89032"
  },
  {
    "LicenseNum": "2000504.054-120 ",
    "MultiJNum": ".",
    "BusinessName": "Focal Media Design Inc. ",
    "PrimaryJurisdiction": "Clark County ",
    "NonPrimaryJurisdiction": " ",
    "LicenseStatus": "Licensed ",
    "BusinessAddress": "2302 Superior Position StNorth Las Vegas, NV 89032"
  },
  {
    "LicenseNum": "2001052.GAM-105 ",
    "MultiJNum": ".",
    "BusinessName": "Foothills Tavern ",
    "PrimaryJurisdiction": "Clark County ",
    "NonPrimaryJurisdiction": " ",
    "LicenseStatus": "Licensed ",
    "BusinessAddress": "2343 W Gowan Rd North Las Vegas, NV 89032"
  },
  {
    "LicenseNum": "1000642.960 ",
    "MultiJNum": ".",
    "BusinessName": "Foster Parents Of Southern Nevada ",
    "PrimaryJurisdiction": "Clark County ",
    "NonPrimaryJurisdiction": " ",
    "LicenseStatus": "Licensed ",
    "BusinessAddress": "4520 San Juan Ave North Las Vegas, NV 89032"
  },
  {
    "LicenseNum": "2002896.507 ",
    "MultiJNum": ".",
    "BusinessName": "Fresh & Clean Services ",
    "PrimaryJurisdiction": "Clark County ",
    "NonPrimaryJurisdiction": " ",
    "LicenseStatus": "Licensed ",
    "BusinessAddress": "2224 Rejoice Dr North Las Vegas, NV 89032"
  },
  {
    "LicenseNum": "2001245.507 ",
    "MultiJNum": ".",
    "BusinessName": "Fresh Start Maintenance ",
    "PrimaryJurisdiction": "Clark County ",
    "NonPrimaryJurisdiction": " ",
    "LicenseStatus": "Licensed ",
    "BusinessAddress": "1130 Hill Bridge Dr North Las Vegas, NV 89032"
  },
  {
    "LicenseNum": "2001225.512 ",
    "MultiJNum": ".",
    "BusinessName": "G & G Landscaping ",
    "PrimaryJurisdiction": "Clark County ",
    "NonPrimaryJurisdiction": " ",
    "LicenseStatus": "Licensed ",
    "BusinessAddress": "1131 Blue Ice Ct North Las Vegas, NV 89032"
  },
  {
    "LicenseNum": "2000718.048-122 ",
    "MultiJNum": ".",
    "BusinessName": "Gary G Babe ",
    "PrimaryJurisdiction": "Clark County ",
    "NonPrimaryJurisdiction": " ",
    "LicenseStatus": "Licensed ",
    "BusinessAddress": "1307 Basin Brook DrNorth Las Vegas, NV 89032"
  },
  {
    "LicenseNum": "2002172.062-101 ",
    "MultiJNum": ".",
    "BusinessName": "Gayle Allen ",
    "PrimaryJurisdiction": "Clark County ",
    "NonPrimaryJurisdiction": " ",
    "LicenseStatus": "Licensed ",
    "BusinessAddress": "4406 Erica DrNorth Las Vegas, NV 89032"
  },
  {
    "LicenseNum": "2001433.GAM-105 ",
    "MultiJNum": ".",
    "BusinessName": "Get N Go Cheyenne ",
    "PrimaryJurisdiction": "Clark County ",
    "NonPrimaryJurisdiction": " ",
    "LicenseStatus": "Licensed ",
    "BusinessAddress": "1450 W Cheyenne AveNorth Las Vegas, NV 89032"
  },
  {
    "LicenseNum": "2000435.048-122 ",
    "MultiJNum": ".",
    "BusinessName": "Giovani Silva Glicerio ",
    "PrimaryJurisdiction": "Clark County ",
    "NonPrimaryJurisdiction": " ",
    "LicenseStatus": "Licensed ",
    "BusinessAddress": "102 Restful Crest AveNorth Las Vegas, NV 89032"
  },
  {
    "LicenseNum": "1012071.510 ",
    "MultiJNum": ".",
    "BusinessName": "Glenn's Pool Service ",
    "PrimaryJurisdiction": "Clark County ",
    "NonPrimaryJurisdiction": " ",
    "LicenseStatus": "Licensed ",
    "BusinessAddress": "3714 Butterball Ct North Las Vegas, NV 89032"
  },
  {
    "LicenseNum": "2000608.845 ",
    "MultiJNum": ".",
    "BusinessName": "Global Pest Services, LLC ",
    "PrimaryJurisdiction": "Clark County ",
    "NonPrimaryJurisdiction": " ",
    "LicenseStatus": "Licensed ",
    "BusinessAddress": "3421 Precision Dr North Las Vegas, NV 89032"
  },
  {
    "LicenseNum": "2001936.GAM-105 ",
    "MultiJNum": ".",
    "BusinessName": "Golden Route Operations ",
    "PrimaryJurisdiction": "Clark County ",
    "NonPrimaryJurisdiction": " ",
    "LicenseStatus": "Licensed ",
    "BusinessAddress": "1570 W Cheyenne AveNorth Las Vegas, NV 89032"
  },
  {
    "LicenseNum": "2000049.847 ",
    "MultiJNum": ".",
    "BusinessName": "Golden Wheels Towing ",
    "PrimaryJurisdiction": "Clark County ",
    "NonPrimaryJurisdiction": " ",
    "LicenseStatus": "Licensed ",
    "BusinessAddress": "2017 W Gowan Rd North Las Vegas, NV 89032"
  },
  {
    "LicenseNum": "1000138.960 ",
    "MultiJNum": ".",
    "BusinessName": "Goodwill Industries of Southern Nevada, Inc. ",
    "PrimaryJurisdiction": "Clark County ",
    "NonPrimaryJurisdiction": " ",
    "LicenseStatus": "Licensed ",
    "BusinessAddress": "1280 W Cheyenne AveNorth Las Vegas, NV 89032"
  },
  {
    "LicenseNum": "2000207.056-101 ",
    "MultiJNum": ".",
    "BusinessName": "Greatfully Dead Pest Control ",
    "PrimaryJurisdiction": "Clark County ",
    "NonPrimaryJurisdiction": " ",
    "LicenseStatus": "Licensed ",
    "BusinessAddress": "4105 Stockman StNorth Las Vegas, NV 89032"
  },
  {
    "LicenseNum": "2000044.549 ",
    "MultiJNum": ".",
    "BusinessName": "Griswold Real Estate Management ",
    "PrimaryJurisdiction": "Clark County ",
    "NonPrimaryJurisdiction": " ",
    "LicenseStatus": "Licensed ",
    "BusinessAddress": "3260 Fountain Falls WyNorth Las Vegas, NV 89032"
  },
  {
    "LicenseNum": "2000305.061-120 ",
    "MultiJNum": ".",
    "BusinessName": "Guns World ",
    "PrimaryJurisdiction": "Clark County ",
    "NonPrimaryJurisdiction": " ",
    "LicenseStatus": "Licensed ",
    "BusinessAddress": "955 W Craig Rd Suite 110 KNorth Las Vegas, NV 89032"
  },
  {
    "LicenseNum": "2001441.048-122 ",
    "MultiJNum": ".",
    "BusinessName": "Haben N Haile ",
    "PrimaryJurisdiction": "Clark County ",
    "NonPrimaryJurisdiction": " ",
    "LicenseStatus": "Licensed ",
    "BusinessAddress": "2116 Regal Vista AveNorth Las Vegas, NV 89032"
  },
  {
    "LicenseNum": "2000539.519 ",
    "MultiJNum": ".",
    "BusinessName": "Hallett, Jo A ",
    "PrimaryJurisdiction": "Clark County ",
    "NonPrimaryJurisdiction": " ",
    "LicenseStatus": "Licensed ",
    "BusinessAddress": "3609 Silver Sand Ct North Las Vegas, NV 89032"
  },
  {
    "LicenseNum": "2000216.411 ",
    "MultiJNum": ".",
    "BusinessName": "Hawg Dawg LLC ",
    "PrimaryJurisdiction": "Clark County ",
    "NonPrimaryJurisdiction": " ",
    "LicenseStatus": "Licensed ",
    "BusinessAddress": "439 Rock Quarry Way North Las Vegas, NV 89032"
  },
  {
    "LicenseNum": "2000145.049-121 ",
    "MultiJNum": ".",
    "BusinessName": "Hector M Salas ",
    "PrimaryJurisdiction": "Clark County ",
    "NonPrimaryJurisdiction": " ",
    "LicenseStatus": "Licensed ",
    "BusinessAddress": "3845 Terrace Canyon StNorth Las Vegas, NV 89032"
  },
  {
    "LicenseNum": "2000756.048-122 ",
    "MultiJNum": ".",
    "BusinessName": "Hector M Salas ",
    "PrimaryJurisdiction": "Clark County ",
    "NonPrimaryJurisdiction": " ",
    "LicenseStatus": "Licensed ",
    "BusinessAddress": "3845 Terrace Canyon StNorth Las Vegas, NV 89032"
  },
  {
    "LicenseNum": "2001427.048-122 ",
    "MultiJNum": ".",
    "BusinessName": "Henry Langsner ",
    "PrimaryJurisdiction": "Clark County ",
    "NonPrimaryJurisdiction": " ",
    "LicenseStatus": "Licensed ",
    "BusinessAddress": "3342 Lute StNorth Las Vegas, NV 89032"
  },
  {
    "LicenseNum": "2000338.056-120 ",
    "MultiJNum": ".",
    "BusinessName": "In Action Landscape Maintenance LLC ",
    "PrimaryJurisdiction": "Clark County ",
    "NonPrimaryJurisdiction": " ",
    "LicenseStatus": "Licensed ",
    "BusinessAddress": "4363 Valley Regents DrLas Vegas, NV 89032"
  },
  {
    "LicenseNum": "2000207.VEN ",
    "MultiJNum": ".",
    "BusinessName": "J.D. Evans A Professional Legal Corporation ",
    "PrimaryJurisdiction": "Clark County ",
    "NonPrimaryJurisdiction": " ",
    "LicenseStatus": "Licensed ",
    "BusinessAddress": "3550 W Cheyenne Ave  Ste 120North Las Vegas, NV 89032"
  },
  {
    "LicenseNum": "2000637.845 ",
    "MultiJNum": ".",
    "BusinessName": "Ja'Mi ",
    "PrimaryJurisdiction": "Clark County ",
    "NonPrimaryJurisdiction": " ",
    "LicenseStatus": "Licensed ",
    "BusinessAddress": "3527 Stampede Ct North Las Vegas, NV 89032"
  },
  {
    "LicenseNum": "2001687.GAM-105 ",
    "MultiJNum": ".",
    "BusinessName": "Jett Gaming, LLC ",
    "PrimaryJurisdiction": "Clark County ",
    "NonPrimaryJurisdiction": " ",
    "LicenseStatus": "Licensed ",
    "BusinessAddress": "335 W Craig Rd North Las Vegas, NV 89032"
  },
  {
    "LicenseNum": "2001534.048-122 ",
    "MultiJNum": ".",
    "BusinessName": "Joel A Tarnate ",
    "PrimaryJurisdiction": "Clark County ",
    "NonPrimaryJurisdiction": " ",
    "LicenseStatus": "Licensed ",
    "BusinessAddress": "3761 Blake Canyon DrNorth Las Vegas, NV 89032"
  },
  {
    "LicenseNum": "2000462.048-122 ",
    "MultiJNum": ".",
    "BusinessName": "Juan Maqueda ",
    "PrimaryJurisdiction": "Clark County ",
    "NonPrimaryJurisdiction": " ",
    "LicenseStatus": "Licensed ",
    "BusinessAddress": "3002 Atwater Dr North Las Vegas, NV 89032"
  },
  {
    "LicenseNum": "2000084.512 ",
    "MultiJNum": ".",
    "BusinessName": "La Familia Lawn Maintenance ",
    "PrimaryJurisdiction": "Clark County ",
    "NonPrimaryJurisdiction": " ",
    "LicenseStatus": "Licensed ",
    "BusinessAddress": "3642 Blairmoor St North Las Vegas, NV 89032"
  },
  {
    "LicenseNum": "2002222.045-101 ",
    "MultiJNum": ".",
    "BusinessName": "Lap of Lux Cigar Lounge LLC ",
    "PrimaryJurisdiction": "Clark County ",
    "NonPrimaryJurisdiction": " ",
    "LicenseStatus": "Licensed ",
    "BusinessAddress": "3697 Blake Canyon DrNorth Las Vegas, NV 89032"
  },
  {
    "LicenseNum": "2000835.048-122 ",
    "MultiJNum": ".",
    "BusinessName": "LeoNard Allen ",
    "PrimaryJurisdiction": "Clark County ",
    "NonPrimaryJurisdiction": " ",
    "LicenseStatus": "Licensed ",
    "BusinessAddress": "1237 W Alexander Rd  Unit 109North Las Vegas, NV 89032"
  },
  {
    "LicenseNum": "2001112.081-121 ",
    "MultiJNum": ".",
    "BusinessName": "Liberty Mobile Detail ",
    "PrimaryJurisdiction": "Clark County ",
    "NonPrimaryJurisdiction": " ",
    "LicenseStatus": "Licensed ",
    "BusinessAddress": "1740 W Nelson Ave North Las Vegas, NV 89032"
  },
  {
    "LicenseNum": "2000075.072-201 ",
    "MultiJNum": ".",
    "BusinessName": "Los Amigos ",
    "PrimaryJurisdiction": "Clark County ",
    "NonPrimaryJurisdiction": " ",
    "LicenseStatus": "Licensed ",
    "BusinessAddress": "439 Rock Quarry Way North Las Vegas, NV 89032"
  },
  {
    "LicenseNum": "2001192.072-201 ",
    "MultiJNum": ".",
    "BusinessName": "Lucy's Ice Cream ",
    "PrimaryJurisdiction": "Clark County ",
    "NonPrimaryJurisdiction": " ",
    "LicenseStatus": "Licensed ",
    "BusinessAddress": "439 Rock Quarry Way North Las Vegas, NV 89032"
  },
  {
    "LicenseNum": "2000473.023-120 ",
    "MultiJNum": ".",
    "BusinessName": "LV Painting LLC ",
    "PrimaryJurisdiction": "Clark County ",
    "NonPrimaryJurisdiction": " ",
    "LicenseStatus": "Licensed ",
    "BusinessAddress": "2101 Hassell Ave North Las Vegas, NV 89032"
  },
  {
    "LicenseNum": "2001467.519 ",
    "MultiJNum": ".",
    "BusinessName": "M. Vincents Professional Massage ",
    "PrimaryJurisdiction": "Clark County ",
    "NonPrimaryJurisdiction": " ",
    "LicenseStatus": "Licensed ",
    "BusinessAddress": "1213 Equator Ave North Las Vegas, NV 89032"
  },
  {
    "LicenseNum": "1002246.GAM-105 ",
    "MultiJNum": ".",
    "BusinessName": "Magoo's Decatur ",
    "PrimaryJurisdiction": "Clark County ",
    "NonPrimaryJurisdiction": " ",
    "LicenseStatus": "Licensed ",
    "BusinessAddress": "3234 N Decatur BlvdNorth Las Vegas, NV 89032"
  },
  {
    "LicenseNum": "2001139.048-122 ",
    "MultiJNum": ".",
    "BusinessName": "Manuel Avellana Perrenoud ",
    "PrimaryJurisdiction": "Clark County ",
    "NonPrimaryJurisdiction": " ",
    "LicenseStatus": "Licensed ",
    "BusinessAddress": "3440 Oakville CtNorth Las Vegas, NV 89032"
  },
  {
    "LicenseNum": "2002138.GAM-105 ",
    "MultiJNum": ".",
    "BusinessName": "Market Gaming, LLC ",
    "PrimaryJurisdiction": "Clark County ",
    "NonPrimaryJurisdiction": " ",
    "LicenseStatus": "Licensed ",
    "BusinessAddress": "3013 W Craig Rd North Las Vegas, NV 89032"
  },
  {
    "LicenseNum": "2002351.062-101 ",
    "MultiJNum": ".",
    "BusinessName": "Massage Par Collette ",
    "PrimaryJurisdiction": "Clark County ",
    "NonPrimaryJurisdiction": " ",
    "LicenseStatus": "Licensed ",
    "BusinessAddress": "3260 Fountain Falls Wy Unit 2053North Las Vegas, NV 89032"
  },
  {
    "LicenseNum": "1000003.034 ",
    "MultiJNum": ".",
    "BusinessName": "MedicWest Ambulance Inc. ",
    "PrimaryJurisdiction": "Clark County ",
    "NonPrimaryJurisdiction": " ",
    "LicenseStatus": "Licensed ",
    "BusinessAddress": "9 W Delhi Ave North Las Vegas, NV 89032"
  },
  {
    "LicenseNum": "1000001.035 ",
    "MultiJNum": ".",
    "BusinessName": "MedicWest Ambulance Inc. ",
    "PrimaryJurisdiction": "Clark County ",
    "NonPrimaryJurisdiction": " ",
    "LicenseStatus": "Licensed ",
    "BusinessAddress": "9 W Delhi Ave North Las Vegas, NV 89032"
  },
  {
    "LicenseNum": "2000010.926-103 ",
    "MultiJNum": ".",
    "BusinessName": "MedicWest Ambulance Inc. (Compliance Penalties) ",
    "PrimaryJurisdiction": "Clark County ",
    "NonPrimaryJurisdiction": " ",
    "LicenseStatus": "Licensed ",
    "BusinessAddress": "9 W Delhi Ave North Las Vegas, NV 89032"
  },
  {
    "LicenseNum": "2002051.048-122 ",
    "MultiJNum": ".",
    "BusinessName": "MIGUEL SILVA ",
    "PrimaryJurisdiction": "Clark County ",
    "NonPrimaryJurisdiction": " ",
    "LicenseStatus": "Licensed ",
    "BusinessAddress": "4116 Coburn StNorth Las Vegas, NV 89032"
  },
  {
    "LicenseNum": "2001376.048-122 ",
    "MultiJNum": ".",
    "BusinessName": "Mitch C Mesce ",
    "PrimaryJurisdiction": "Clark County ",
    "NonPrimaryJurisdiction": " ",
    "LicenseStatus": "Licensed ",
    "BusinessAddress": "4712 Erica DrNorth Las Vegas, NV 89032"
  },
  {
    "LicenseNum": "2001585.054-120 ",
    "MultiJNum": ".",
    "BusinessName": "MY GUY ARC ",
    "PrimaryJurisdiction": "Clark County ",
    "NonPrimaryJurisdiction": " ",
    "LicenseStatus": "Revoked - Delinquent ",
    "BusinessAddress": "3631 Cool Vista CtNorth Las Vegas, NV 89032"
  },
  {
    "LicenseNum": "2000241.960 ",
    "MultiJNum": ".",
    "BusinessName": "National Wild Horse Association ",
    "PrimaryJurisdiction": "Clark County ",
    "NonPrimaryJurisdiction": " ",
    "LicenseStatus": "Licensed ",
    "BusinessAddress": "4016 San Diego St North Las Vegas, NV 89032"
  },
  {
    "LicenseNum": "1000573.577 ",
    "MultiJNum": ".",
    "BusinessName": "Network I & D, LLC ",
    "PrimaryJurisdiction": "Clark County ",
    "NonPrimaryJurisdiction": " ",
    "LicenseStatus": "Licensed ",
    "BusinessAddress": "4318 W Cheyenne Ave North Las Vegas, NV 89032"
  },
  {
    "LicenseNum": "2000385.061-120 ",
    "MultiJNum": ".",
    "BusinessName": "Nevada Marksmanship Training ",
    "PrimaryJurisdiction": "Clark County ",
    "NonPrimaryJurisdiction": " ",
    "LicenseStatus": "Licensed ",
    "BusinessAddress": "4145 Oak Bay WayNorth Las Vegas, NV 89032"
  },
  {
    "LicenseNum": "2002814.062-120 ",
    "MultiJNum": ".",
    "BusinessName": "New Foundation Choice ",
    "PrimaryJurisdiction": "Clark County ",
    "NonPrimaryJurisdiction": " ",
    "LicenseStatus": "Licensed ",
    "BusinessAddress": "3925 N Martin L King Blvd Suite 118North Las Vegas, NV 89032"
  },
  {
    "LicenseNum": "2000043.062-101 ",
    "MultiJNum": ".",
    "BusinessName": "New Visions BHA ",
    "PrimaryJurisdiction": "Clark County ",
    "NonPrimaryJurisdiction": " ",
    "LicenseStatus": "Licensed ",
    "BusinessAddress": "3925 N Martin Luther King Blvd Suite 208North Las Vegas, NV 89032"
  },
  {
    "LicenseNum": "2000063.841 ",
    "MultiJNum": ".",
    "BusinessName": "Oasis Moving And Storage Inc ",
    "PrimaryJurisdiction": "Clark County ",
    "NonPrimaryJurisdiction": " ",
    "LicenseStatus": "Licensed ",
    "BusinessAddress": "2915 Coleman St North Las Vegas, NV 89032"
  },
  {
    "LicenseNum": "2000670.071-121 ",
    "MultiJNum": ".",
    "BusinessName": "OneNationGroup LLC ",
    "PrimaryJurisdiction": "Clark County ",
    "NonPrimaryJurisdiction": " ",
    "LicenseStatus": "Licensed ",
    "BusinessAddress": "3956 Valley DrNorth Las Vegas, NV 89032"
  },
  {
    "LicenseNum": "2001811.044-101 ",
    "MultiJNum": ".",
    "BusinessName": "Otte Mobile Mix ",
    "PrimaryJurisdiction": "Clark County ",
    "NonPrimaryJurisdiction": " ",
    "LicenseStatus": "Licensed ",
    "BusinessAddress": "120 W Delhi AveNorth Las Vegas, NV 89032"
  },
  {
    "LicenseNum": "2000993.100 ",
    "MultiJNum": ".",
    "BusinessName": "Oviedo's Mobile Car Wash ",
    "PrimaryJurisdiction": "Clark County ",
    "NonPrimaryJurisdiction": " ",
    "LicenseStatus": "Licensed ",
    "BusinessAddress": "1124 Coral Crystal Ct North Las Vegas, NV 89032"
  },
  {
    "LicenseNum": "2000005.319 ",
    "MultiJNum": ".",
    "BusinessName": "Pinnacle Community Services Limited Partnership ",
    "PrimaryJurisdiction": "Clark County ",
    "NonPrimaryJurisdiction": " ",
    "LicenseStatus": "Licensed ",
    "BusinessAddress": "3435 W Cheyenne Ave Ste 103North Las Vegas, NV 89032"
  },
  {
    "LicenseNum": "2002749.062-101 ",
    "MultiJNum": ".",
    "BusinessName": "Plaisance Therapeutic Massage ",
    "PrimaryJurisdiction": "Clark County ",
    "NonPrimaryJurisdiction": " ",
    "LicenseStatus": "Licensed ",
    "BusinessAddress": "2258 Knoll Crest AveNorth Las Vegas, NV 89032"
  },
  {
    "LicenseNum": "2001629.519 ",
    "MultiJNum": ".",
    "BusinessName": "Quality EFX ",
    "PrimaryJurisdiction": "Clark County ",
    "NonPrimaryJurisdiction": " ",
    "LicenseStatus": "Licensed ",
    "BusinessAddress": "3515 Rose Canyon Dr North Las Vegas, NV 89032"
  },
  {
    "LicenseNum": "1001013.512 ",
    "MultiJNum": ".",
    "BusinessName": "R P Lang Inc ",
    "PrimaryJurisdiction": "Clark County ",
    "NonPrimaryJurisdiction": " ",
    "LicenseStatus": "Licensed ",
    "BusinessAddress": "2810 Perimeter Rd Ste 101North Las Vegas, NV 89032"
  },
  {
    "LicenseNum": "2000428.048-122 ",
    "MultiJNum": ".",
    "BusinessName": "Randal  F Wright ",
    "PrimaryJurisdiction": "Clark County ",
    "NonPrimaryJurisdiction": " ",
    "LicenseStatus": "Licensed ",
    "BusinessAddress": "3710 Lake Victoria DrNorth Las Vegas, NV 89032"
  },
  {
    "LicenseNum": "2001187.GAM-105 ",
    "MultiJNum": ".",
    "BusinessName": "Rebel Oil Co., Inc. ",
    "PrimaryJurisdiction": "Clark County ",
    "NonPrimaryJurisdiction": " ",
    "LicenseStatus": "Licensed ",
    "BusinessAddress": "2810 N Rancho DrNorth Las Vegas, NV 89032"
  },
  {
    "LicenseNum": "2000383.061-120 ",
    "MultiJNum": ".",
    "BusinessName": "Rich Taylor ",
    "PrimaryJurisdiction": "Clark County ",
    "NonPrimaryJurisdiction": " ",
    "LicenseStatus": "Licensed ",
    "BusinessAddress": "1523 Bradfox Ln North Las Vegas, NV 89032"
  },
  {
    "LicenseNum": "2000092.023-120 ",
    "MultiJNum": ".",
    "BusinessName": "Richard Sievers Home Repair, LLC ",
    "PrimaryJurisdiction": "Clark County ",
    "NonPrimaryJurisdiction": " ",
    "LicenseStatus": "Licensed ",
    "BusinessAddress": "4111 Bola DrNorth Las Vegas, NV 89032"
  },
  {
    "LicenseNum": "2000246.341 ",
    "MultiJNum": ".",
    "BusinessName": "Richardson Construction Inc. ",
    "PrimaryJurisdiction": "Clark County ",
    "NonPrimaryJurisdiction": " ",
    "LicenseStatus": "Licensed ",
    "BusinessAddress": "2207 W Gowan Rd North Las Vegas, NV 89032"
  },
  {
    "LicenseNum": "2000689.165 ",
    "MultiJNum": ".",
    "BusinessName": "Rmi Operating Company, LLC ",
    "PrimaryJurisdiction": "Clark County ",
    "NonPrimaryJurisdiction": " ",
    "LicenseStatus": "Revoked - Delinquent ",
    "BusinessAddress": "109 W Delhi Ave North Las Vegas, NV 89032"
  },
  {
    "LicenseNum": "2000329.048-122 ",
    "MultiJNum": ".",
    "BusinessName": "Robert Franks ",
    "PrimaryJurisdiction": "Clark County ",
    "NonPrimaryJurisdiction": " ",
    "LicenseStatus": "Licensed ",
    "BusinessAddress": "1216 Satellite AveNorth Las Vegas, NV 89032"
  },
  {
    "LicenseNum": "2000334.048-122 ",
    "MultiJNum": ".",
    "BusinessName": "Robert J Dalbec ",
    "PrimaryJurisdiction": "Clark County ",
    "NonPrimaryJurisdiction": " ",
    "LicenseStatus": "Licensed ",
    "BusinessAddress": "4205 Thomas Patrick AveNorth Las Vegas, NV 89032"
  },
  {
    "LicenseNum": "2002010.056-120 ",
    "MultiJNum": ".",
    "BusinessName": "Roberto's Lawn Maintenance Services ",
    "PrimaryJurisdiction": "Clark County ",
    "NonPrimaryJurisdiction": " ",
    "LicenseStatus": "Licensed ",
    "BusinessAddress": "1909 Hassell AveNorth Las Vegas, NV 89032"
  },
  {
    "LicenseNum": "2001101.072-201 ",
    "MultiJNum": ".",
    "BusinessName": "Rolling Fusion ",
    "PrimaryJurisdiction": "Clark County ",
    "NonPrimaryJurisdiction": " ",
    "LicenseStatus": "Revoked - Delinquent ",
    "BusinessAddress": "439 Rock Quarry Way North Las Vegas, NV 89032"
  },
  {
    "LicenseNum": "2001531.072-201 ",
    "MultiJNum": ".",
    "BusinessName": "Ruby's Taco Shop ",
    "PrimaryJurisdiction": "Clark County ",
    "NonPrimaryJurisdiction": " ",
    "LicenseStatus": "Licensed ",
    "BusinessAddress": "439 Rock Quarry WyNorth Las Vegas, NV 89032"
  },
  {
    "LicenseNum": "2000215.048-171 ",
    "MultiJNum": ".",
    "BusinessName": "Ryan's Express & Divine Transportation ",
    "PrimaryJurisdiction": "Clark County ",
    "NonPrimaryJurisdiction": " ",
    "LicenseStatus": "Revoked - Delinquent ",
    "BusinessAddress": "412 E Gowan Rd North Las Vegas, NV 89032"
  },
  {
    "LicenseNum": "2001648.062-101 ",
    "MultiJNum": ".",
    "BusinessName": "Sabrina Reedy ",
    "PrimaryJurisdiction": "Clark County ",
    "NonPrimaryJurisdiction": " ",
    "LicenseStatus": "Licensed ",
    "BusinessAddress": "3817 Juanita May AveNorth Las Vegas, NV 89032"
  },
  {
    "LicenseNum": "2001096.512 ",
    "MultiJNum": ".",
    "BusinessName": "Salero ",
    "PrimaryJurisdiction": "Clark County ",
    "NonPrimaryJurisdiction": " ",
    "LicenseStatus": "Licensed ",
    "BusinessAddress": "3914 Royal Stone Ct North Las Vegas, NV 89032"
  },
  {
    "LicenseNum": "2001017.062-120 ",
    "MultiJNum": ".",
    "BusinessName": "San Antonio Personal Care ",
    "PrimaryJurisdiction": "Clark County ",
    "NonPrimaryJurisdiction": " ",
    "LicenseStatus": "Licensed ",
    "BusinessAddress": "417 Foxvale AveNorth Las Vegas, NV 89032"
  },
  {
    "LicenseNum": "2002011.GAM-105 ",
    "MultiJNum": ".",
    "BusinessName": "Sartini Gaming, LLC ",
    "PrimaryJurisdiction": "Clark County ",
    "NonPrimaryJurisdiction": " ",
    "LicenseStatus": "Licensed ",
    "BusinessAddress": "785 W Craig RdNorth Las Vegas, NV 89032"
  },
  {
    "LicenseNum": "2001905.056-120 ",
    "MultiJNum": ".",
    "BusinessName": "Servpro of of Downtown Las Vegas ",
    "PrimaryJurisdiction": "Clark County ",
    "NonPrimaryJurisdiction": " ",
    "LicenseStatus": "Licensed ",
    "BusinessAddress": "3395 W Cheyenne AveNorth Las Vegas, NV 89032"
  },
  {
    "LicenseNum": "2000761.056-120 ",
    "MultiJNum": ".",
    "BusinessName": "SET-UP Inc ",
    "PrimaryJurisdiction": "Clark County ",
    "NonPrimaryJurisdiction": " ",
    "LicenseStatus": "Licensed ",
    "BusinessAddress": "4017 San Mateo St North Las Vegas, NV 89032"
  },
  {
    "LicenseNum": "2001020.048-122 ",
    "MultiJNum": ".",
    "BusinessName": "Sherwood Lynn Atkinson ",
    "PrimaryJurisdiction": "Clark County ",
    "NonPrimaryJurisdiction": " ",
    "LicenseStatus": "Licensed ",
    "BusinessAddress": "4165 Fuselier DrNorth Las Vegas, NV 89032"
  },
  {
    "LicenseNum": "2000075.032 ",
    "MultiJNum": ".",
    "BusinessName": "Shield Fire & Security ",
    "PrimaryJurisdiction": "Clark County ",
    "NonPrimaryJurisdiction": " ",
    "LicenseStatus": "Licensed ",
    "BusinessAddress": "3395 W Cheyenne Ave Ste 109North Las Vegas, NV 89032"
  },
  {
    "LicenseNum": "1002377.GAM-105 ",
    "MultiJNum": ".",
    "BusinessName": "Short Line Express Market #3 ",
    "PrimaryJurisdiction": "Clark County ",
    "NonPrimaryJurisdiction": " ",
    "LicenseStatus": "Licensed ",
    "BusinessAddress": "3965 N Martin L King Blvd North Las Vegas, NV 89032"
  },
  {
    "LicenseNum": "2000603.GAM-105 ",
    "MultiJNum": ".",
    "BusinessName": "Short Line Express Market #9 ",
    "PrimaryJurisdiction": "Clark County ",
    "NonPrimaryJurisdiction": " ",
    "LicenseStatus": "Licensed ",
    "BusinessAddress": "2865 W Cheyenne Ave North Las Vegas, NV 89032"
  },
  {
    "LicenseNum": "2000794.507 ",
    "MultiJNum": ".",
    "BusinessName": "Simply Clean Building Service ",
    "PrimaryJurisdiction": "Clark County ",
    "NonPrimaryJurisdiction": " ",
    "LicenseStatus": "Licensed ",
    "BusinessAddress": "4631 Chestnut Blaze Dr North Las Vegas, NV 89032"
  },
  {
    "LicenseNum": "2000835.GAM-105 ",
    "MultiJNum": ".",
    "BusinessName": "Speedee Mart #117 ",
    "PrimaryJurisdiction": "Clark County ",
    "NonPrimaryJurisdiction": " ",
    "LicenseStatus": "Licensed ",
    "BusinessAddress": "2841 W Craig Rd North Las Vegas, NV 89032"
  },
  {
    "LicenseNum": "2001058.GAM-105 ",
    "MultiJNum": ".",
    "BusinessName": "Sporting Chance Saloon ",
    "PrimaryJurisdiction": "Clark County ",
    "NonPrimaryJurisdiction": " ",
    "LicenseStatus": "Licensed ",
    "BusinessAddress": "2808 W Craig RdNorth Las Vegas, NV 89032"
  },
  {
    "LicenseNum": "2000940.056-120 ",
    "MultiJNum": ".",
    "BusinessName": "SRL Lawn Maintenance ",
    "PrimaryJurisdiction": "Clark County ",
    "NonPrimaryJurisdiction": " ",
    "LicenseStatus": "Licensed ",
    "BusinessAddress": "4340 Silvercrest CtNorth Las Vegas, NV 89032"
  },
  {
    "LicenseNum": "2001450.048-122 ",
    "MultiJNum": ".",
    "BusinessName": "Stacey Watson ",
    "PrimaryJurisdiction": "Clark County ",
    "NonPrimaryJurisdiction": " ",
    "LicenseStatus": "Licensed ",
    "BusinessAddress": "3260 Fountain Falls Wy Apt 1097North Las Vegas, NV 89032"
  },
  {
    "LicenseNum": "1001121.510 ",
    "MultiJNum": ".",
    "BusinessName": "Stanley Steemer Carpet Cleaner ",
    "PrimaryJurisdiction": "Clark County ",
    "NonPrimaryJurisdiction": " ",
    "LicenseStatus": "Licensed ",
    "BusinessAddress": "425 W Gowan Rd North Las Vegas, NV 89032"
  },
  {
    "LicenseNum": "1002071.GAM-105 ",
    "MultiJNum": ".",
    "BusinessName": "Sundance Kid Cafe ",
    "PrimaryJurisdiction": "Clark County ",
    "NonPrimaryJurisdiction": " ",
    "LicenseStatus": "Licensed ",
    "BusinessAddress": "4325 W Craig Rd North Las Vegas, NV 89032"
  },
  {
    "LicenseNum": "2000025.263 ",
    "MultiJNum": ".",
    "BusinessName": "Sundance Surveying, Inc. ",
    "PrimaryJurisdiction": "Clark County ",
    "NonPrimaryJurisdiction": " ",
    "LicenseStatus": "Licensed ",
    "BusinessAddress": "3832 Valley Dr North Las Vegas, NV 89032"
  },
  {
    "LicenseNum": "2000870.056-120 ",
    "MultiJNum": ".",
    "BusinessName": "Sunshine Janitorial Service, LLC ",
    "PrimaryJurisdiction": "Clark County ",
    "NonPrimaryJurisdiction": " ",
    "LicenseStatus": "Licensed ",
    "BusinessAddress": "3909 Jamison Park LnNorth Las Vegas, NV 89032"
  },
  {
    "LicenseNum": "2001490.056-120 ",
    "MultiJNum": ".",
    "BusinessName": "Supreme Carpet Cleaning LLC ",
    "PrimaryJurisdiction": "Clark County ",
    "NonPrimaryJurisdiction": " ",
    "LicenseStatus": "Licensed ",
    "BusinessAddress": "3355 Clayton St Unit #12North Las Vegas, NV 89032"
  },
  {
    "LicenseNum": "1004169.GAM-105 ",
    "MultiJNum": ".",
    "BusinessName": "Surf City Bar & Grill ",
    "PrimaryJurisdiction": "Clark County ",
    "NonPrimaryJurisdiction": " ",
    "LicenseStatus": "Licensed ",
    "BusinessAddress": "1435 W Craig Rd  DNorth Las Vegas, NV 89032"
  },
  {
    "LicenseNum": "2003707.507 ",
    "MultiJNum": ".",
    "BusinessName": "Surface Magic, Inc. ",
    "PrimaryJurisdiction": "Clark County ",
    "NonPrimaryJurisdiction": " ",
    "LicenseStatus": "Licensed ",
    "BusinessAddress": "1122 Elliot Park Ave North Las Vegas, NV 89032"
  },
  {
    "LicenseNum": "1000034.355 ",
    "MultiJNum": ".",
    "BusinessName": "Swat Bug Killers Inc ",
    "PrimaryJurisdiction": "Clark County ",
    "NonPrimaryJurisdiction": " ",
    "LicenseStatus": "Licensed ",
    "BusinessAddress": "3520 Coleman StNorth Las Vegas, NV 89032"
  },
  {
    "LicenseNum": "2000005.411 ",
    "MultiJNum": ".",
    "BusinessName": "Tacos Colima ",
    "PrimaryJurisdiction": "Clark County ",
    "NonPrimaryJurisdiction": " ",
    "LicenseStatus": "Licensed ",
    "BusinessAddress": "439 Rock Quarry Way North Las Vegas, NV 89032"
  },
  {
    "LicenseNum": "1001962.GAM-105 ",
    "MultiJNum": ".",
    "BusinessName": "Texas Gambling Hall & Hotel ",
    "PrimaryJurisdiction": "Clark County ",
    "NonPrimaryJurisdiction": " ",
    "LicenseStatus": "Licensed ",
    "BusinessAddress": "2101 Texas Star Ln North Las Vegas, NV 89032"
  },
  {
    "LicenseNum": "1000482.865 ",
    "MultiJNum": ".",
    "BusinessName": "Thirsty's Water ",
    "PrimaryJurisdiction": "Clark County ",
    "NonPrimaryJurisdiction": " ",
    "LicenseStatus": "Licensed ",
    "BusinessAddress": "3310 Kemp St North Las Vegas, NV 89032"
  },
  {
    "LicenseNum": "2001064.048-122 ",
    "MultiJNum": ".",
    "BusinessName": "TIMOTHY PETER MENDELL ",
    "PrimaryJurisdiction": "Clark County ",
    "NonPrimaryJurisdiction": " ",
    "LicenseStatus": "Licensed ",
    "BusinessAddress": "3911 MCGREGOR WYNorth Las Vegas, NV 89032"
  },
  {
    "LicenseNum": "2000561.845 ",
    "MultiJNum": ".",
    "BusinessName": "Tire's 4 Hire Mobile Tire Repair L.L.C. ",
    "PrimaryJurisdiction": "Clark County ",
    "NonPrimaryJurisdiction": " ",
    "LicenseStatus": "Licensed ",
    "BusinessAddress": "1831 Double Delight Ave North Las Vegas, NV 89032"
  },
  {
    "LicenseNum": "2001193.023-120 ",
    "MultiJNum": ".",
    "BusinessName": "TLS Nevada ",
    "PrimaryJurisdiction": "Clark County ",
    "NonPrimaryJurisdiction": " ",
    "LicenseStatus": "Licensed ",
    "BusinessAddress": "3650 N 5th St Suite 140North Las Vegas, NV 89032"
  },
  {
    "LicenseNum": "2001526.054-190 ",
    "MultiJNum": ".",
    "BusinessName": "Trinity Land Surveying Inc. (TLS) ",
    "PrimaryJurisdiction": "Clark County ",
    "NonPrimaryJurisdiction": " ",
    "LicenseStatus": "Revoked - Delinquent ",
    "BusinessAddress": "3650 N 5th St Suite 140North Las Vegas, NV 89032"
  },
  {
    "LicenseNum": "2000035.841 ",
    "MultiJNum": ".",
    "BusinessName": "Two Men And A Truck ",
    "PrimaryJurisdiction": "Clark County ",
    "NonPrimaryJurisdiction": " ",
    "LicenseStatus": "Licensed ",
    "BusinessAddress": "3510 Coleman StNorth Las Vegas, NV 89032"
  },
  {
    "LicenseNum": "2000113.847 ",
    "MultiJNum": ".",
    "BusinessName": "U.S.A. Towing, Inc ",
    "PrimaryJurisdiction": "Clark County ",
    "NonPrimaryJurisdiction": " ",
    "LicenseStatus": "Licensed ",
    "BusinessAddress": "2105 W Gowan Rd North Las Vegas, NV 89032"
  },
  {
    "LicenseNum": "2000031.547 ",
    "MultiJNum": ".",
    "BusinessName": "V-Tech Construction Inc Commercial & Residential ",
    "PrimaryJurisdiction": "Clark County ",
    "NonPrimaryJurisdiction": " ",
    "LicenseStatus": "Licensed ",
    "BusinessAddress": "1420 Broad Arrow Dr North Las Vegas, NV 89032"
  },
  {
    "LicenseNum": "2000968.512 ",
    "MultiJNum": ".",
    "BusinessName": "Vegas Garden ",
    "PrimaryJurisdiction": "Clark County ",
    "NonPrimaryJurisdiction": " ",
    "LicenseStatus": "Licensed ",
    "BusinessAddress": "3535 Calf Roper CtNorth Las Vegas, NV 89032"
  },
  {
    "LicenseNum": "2000020.030 ",
    "MultiJNum": ".",
    "BusinessName": "Vision Air ",
    "PrimaryJurisdiction": "Clark County ",
    "NonPrimaryJurisdiction": " ",
    "LicenseStatus": "Licensed ",
    "BusinessAddress": "2705 Airport DrNorth Las Vegas, NV 89032"
  },
  {
    "LicenseNum": "2000083.832 ",
    "MultiJNum": ".",
    "BusinessName": "Vision Holidays, Inc. ",
    "PrimaryJurisdiction": "Clark County ",
    "NonPrimaryJurisdiction": " ",
    "LicenseStatus": "Licensed ",
    "BusinessAddress": "2705 Airport DrNorth Las Vegas, NV 89032"
  },
  {
    "LicenseNum": "2000284.042-101 ",
    "MultiJNum": ".",
    "BusinessName": "Weller Truck Parts ",
    "PrimaryJurisdiction": "Clark County ",
    "NonPrimaryJurisdiction": " ",
    "LicenseStatus": "Licensed ",
    "BusinessAddress": "2985 Coleman St  Ste 14North Las Vegas, NV 89032"
  },
  {
    "LicenseNum": "2000151.355 ",
    "MultiJNum": ".",
    "BusinessName": "What's Bugging You? ",
    "PrimaryJurisdiction": "Clark County ",
    "NonPrimaryJurisdiction": " ",
    "LicenseStatus": "Licensed ",
    "BusinessAddress": "1530 Bradfox Ln North Las Vegas, NV 89032"
  },
  {
    "LicenseNum": "2000393.VEN-101 ",
    "MultiJNum": ".",
    "BusinessName": "William Lewis Wolfbrandt, Jr., Prof. Corp. ",
    "PrimaryJurisdiction": "Clark County ",
    "NonPrimaryJurisdiction": " ",
    "LicenseStatus": "Licensed ",
    "BusinessAddress": "3550 W Cheyenne Ave  #110North Las Vegas, NV 89032"
  },
  {
    "LicenseNum": "2000542.960 ",
    "MultiJNum": ".",
    "BusinessName": "Youth Advocate Programs, Inc ",
    "PrimaryJurisdiction": "Clark County ",
    "NonPrimaryJurisdiction": " ",
    "LicenseStatus": "Licensed ",
    "BusinessAddress": "2535 W Cheyenne Ave North Las Vegas, NV 89032"
  }
]